Metadata-Version: 1.0
Name: Flask-BrowserID
Version: 0.0.4
Summary: Flask support for BrowserID authentication
Home-page: https://github.com/garbados/flask-browserid
Author: Max Thayer
Author-email: garbados@gmail.com
License: MIT
Platform: any
Classifier: Environment :: Web Environment
Classifier: Intended Audience :: Developers
Classifier: Operating System :: OS Independent
Classifier: Programming Language :: Python
Classifier: Topic :: Internet :: WWW/HTTP :: Dynamic Content
Classifier: Topic :: Software Development :: Libraries :: Python Modules
